beatit.py
beatit-2022.3.1.dist-info/LICENSE
beatit-2022.3.1.dist-info/WHEEL
beatit-2022.3.1.dist-info/METADATA
beatit-2022.3.1.dist-info/RECORD
