Metadata-Version: 2.1
Name: beatit
Version: 2022.3.1
Summary: A simple backend agnostic heartbeating convention
Author-email: Eugene Van den Bulke <eugene.vandenbulke@gmail.com>
Project-URL: Home, https://github.com/3kwa/beatit
